README.md
setup.py
cw_testtool/AEStool.py
cw_testtool/HttpServer.py
cw_testtool/NetWorkTest.py
cw_testtool/RSAtool.py
cw_testtool/SocketClientDemo.py
cw_testtool/SocketServerDemo.py
cw_testtool/SystemMsgTool.py
cw_testtool/__init__.py
cw_testtool/dbTool.py
cw_testtool/importFile.py
cw_testtool/klinetool.py
cw_testtool/listtool.py
cw_testtool/okexUtil.py
cw_testtool/pathtool.py
cw_testtool/pytimer.py
cw_testtool/systool.py
cw_testtool/timetool.py
cw_testtool/urltool.py
cw_testtool/uuidTool.py
cw_testtool.egg-info/PKG-INFO
cw_testtool.egg-info/SOURCES.txt
cw_testtool.egg-info/dependency_links.txt
cw_testtool.egg-info/requires.txt
cw_testtool.egg-info/top_level.txt