Metadata-Version: 1.0
Name: cw-testtool
Version: 0.1.41
Summary: time and path tool
Home-page: https://github.com/1294936122/test
Author: jack_chen
Author-email: 1390212397@qq.com
License: MIT Licence
Keywords: pathtool,timetool,magetool,mage
Platform: any
